[
  {
    "target": "fire",
    "selected_associate": "fire",
    "inferred_recovery_label": "fire",
    "recovery_inference_source": "recent_history",
    "hypothesis_label": "explain:fire",
    "correct_concept": true,
    "inferred_correct": true,
    "autonomous_inference": true,
    "early_recovery_full": 0.967117853285347,
    "early_recovery_ablated": 6958.07711372973,
    "improvement_percent": 99.9861007885156,
    "beats_ablation": true,
    "pass": true
  },
  {
    "target": "water",
    "selected_associate": "water",
    "inferred_recovery_label": "water",
    "recovery_inference_source": "recent_history",
    "hypothesis_label": "explain:water",
    "correct_concept": true,
    "inferred_correct": true,
    "autonomous_inference": true,
    "early_recovery_full": 1.045615328050939,
    "early_recovery_ablated": 14232.422350518822,
    "improvement_percent": 99.99265328626218,
    "beats_ablation": true,
    "pass": true
  },
  {
    "target": "smoke",
    "selected_associate": "smoke",
    "inferred_recovery_label": "smoke",
    "recovery_inference_source": "recent_history",
    "hypothesis_label": "explain:smoke",
    "correct_concept": true,
    "inferred_correct": true,
    "autonomous_inference": true,
    "early_recovery_full": 2.3042001144320308,
    "early_recovery_ablated": 1396.6572834312415,
    "improvement_percent": 99.83502036313654,
    "beats_ablation": true,
    "pass": true
  }
]